snektalk/__init__.py
snektalk/analyze.py
snektalk/assets/favicon.ico
snektalk/assets/index.html
snektalk/assets/lib/mousetrap.min.js
snektalk/assets/lib/require.min.js
snektalk/assets/lib/split-grid.min.js
snektalk/assets/lib/vs/base/browser/ui/codicons/codicon/codicon.ttf
snektalk/assets/lib/vs/base/worker/workerMain.js
snektalk/assets/lib/vs/basic-languages/abap/abap.js
snektalk/assets/lib/vs/basic-languages/apex/apex.js
snektalk/assets/lib/vs/basic-languages/azcli/azcli.js
snektalk/assets/lib/vs/basic-languages/bat/bat.js
snektalk/assets/lib/vs/basic-languages/cameligo/cameligo.js
snektalk/assets/lib/vs/basic-languages/clojure/clojure.js
snektalk/assets/lib/vs/basic-languages/coffee/coffee.js
snektalk/assets/lib/vs/basic-languages/cpp/cpp.js
snektalk/assets/lib/vs/basic-languages/csharp/csharp.js
snektalk/assets/lib/vs/basic-languages/csp/csp.js
snektalk/assets/lib/vs/basic-languages/css/css.js
snektalk/assets/lib/vs/basic-languages/dart/dart.js
snektalk/assets/lib/vs/basic-languages/dockerfile/dockerfile.js
snektalk/assets/lib/vs/basic-languages/ecl/ecl.js
snektalk/assets/lib/vs/basic-languages/fsharp/fsharp.js
snektalk/assets/lib/vs/basic-languages/go/go.js
snektalk/assets/lib/vs/basic-languages/graphql/graphql.js
snektalk/assets/lib/vs/basic-languages/handlebars/handlebars.js
snektalk/assets/lib/vs/basic-languages/hcl/hcl.js
snektalk/assets/lib/vs/basic-languages/html/html.js
snektalk/assets/lib/vs/basic-languages/ini/ini.js
snektalk/assets/lib/vs/basic-languages/java/java.js
snektalk/assets/lib/vs/basic-languages/javascript/javascript.js
snektalk/assets/lib/vs/basic-languages/julia/julia.js
snektalk/assets/lib/vs/basic-languages/kotlin/kotlin.js
snektalk/assets/lib/vs/basic-languages/less/less.js
snektalk/assets/lib/vs/basic-languages/lexon/lexon.js
snektalk/assets/lib/vs/basic-languages/lua/lua.js
snektalk/assets/lib/vs/basic-languages/m3/m3.js
snektalk/assets/lib/vs/basic-languages/markdown/markdown.js
snektalk/assets/lib/vs/basic-languages/mips/mips.js
snektalk-0.0.16.dist-info/entry_points.txt
snektalk-0.0.16.dist-info/WHEEL
snektalk-0.0.16.dist-info/METADATA
snektalk-0.0.16.dist-info/RECORD
